{
  "token": "emacs-app-good",
  "full_token": "jimeh/emacs-builds/emacs-app-good",
  "old_tokens": [],
  "tap": "jimeh/emacs-builds",
  "name": [
    "Emacs"
  ],
  "desc": "GNU Emacs text editor (known good nightly build)",
  "homepage": "https://github.com/jimeh/emacs-builds",
  "url": "https://github.com/jimeh/emacs-builds/releases/download/Emacs.2023-05-30.ecc1d99.master/Emacs.2023-05-30.ecc1d99.master.macOS-11.x86_64.dmg",
  "url_specs": {},
  "appcast": null,
  "version": "2023-05-30.ecc1d99.master",
  "installed": null,
  "outdated": false,
  "sha256": "4941b57bcab80bf7f5bcdbd3908c6e90bb754c6a37cc98d0b183ed254af65c40",
  "artifacts": [
    {
      "app": [
        "Emacs.app"
      ]
    },
    {
      "binary": [
        "/Applications/Emacs.app/Contents/MacOS/bin/ebrowse"
      ]
    },
    {
      "binary": [
        "/Applications/Emacs.app/Contents/MacOS/bin/emacs"
      ]
    },
    {
      "binary": [
        "/Applications/Emacs.app/Contents/MacOS/bin/emacsclient"
      ]
    },
    {
      "binary": [
        "/Applications/Emacs.app/Contents/MacOS/bin/etags"
      ]
    },
    {
      "binary": [
        "/Applications/Emacs.app/Contents/Resources/include/emacs-module.h",
        {
          "target": "/usr/local/include/emacs-module.h"
        }
      ]
    },
    {
      "binary": [
        "/Applications/Emacs.app/Contents/Resources/site-lisp/subdirs.el",
        {
          "target": "/usr/local/share/emacs/site-lisp/subdirs.el"
        }
      ]
    },
    {
      "manpage": [
        "/Applications/Emacs.app/Contents/Resources/man/man1/ebrowse.1.gz"
      ]
    },
    {
      "manpage": [
        "/Applications/Emacs.app/Contents/Resources/man/man1/emacs.1.gz"
      ]
    },
    {
      "manpage": [
        "/Applications/Emacs.app/Contents/Resources/man/man1/emacsclient.1.gz"
      ]
    },
    {
      "manpage": [
        "/Applications/Emacs.app/Contents/Resources/man/man1/etags.1.gz"
      ]
    },
    {
      "zap": [
        {
          "trash": [
            "~/Library/Caches/org.gnu.Emacs",
            "~/Library/Preferences/org.gnu.Emacs.plist",
            "~/Library/Saved Application State/org.gnu.Emacs.savedState"
          ]
        }
      ]
    }
  ],
  "caveats": null,
  "depends_on": {
    "macos": {
      ">=": [
        "11"
      ]
    }
  },
  "conflicts_with": {
    "cask": [
      "emacs-app",
      "emacs-app-nightly",
      "emacs-app-nightly-28",
      "emacs-app-nightly-29",
      "emacs-app-pretest",
      "emacs",
      "emacs-nightly",
      "emacs-pretest",
      "emacs-mac",
      "emacs-mac-spacemacs-icon"
    ],
    "formula": [
      "emacs",
      "emacs-mac"
    ]
  },
  "container": null,
  "auto_updates": null,
  "tap_git_head": "59035b5694654332cd96189824daf630453a0d22",
  "languages": [],
  "ruby_source_path": "Casks/emacs-app-good.rb",
  "ruby_source_checksum": {
    "sha256": "3997000ee12cbbab432455aefc5b2617e81a9f09e28642386581397a29c6535e"
  }
}
