{
  "token": "emacs-app-nightly",
  "full_token": "jimeh/emacs-builds/emacs-app-nightly",
  "tap": "jimeh/emacs-builds",
  "name": [
    "Emacs"
  ],
  "desc": "GNU Emacs text editor (nightly build)",
  "homepage": "https://github.com/jimeh/emacs-builds",
  "url": "https://github.com/jimeh/emacs-builds/releases/download/Emacs.2023-05-14.e7dc30c.master/Emacs.2023-05-14.e7dc30c.master.macOS-11.x86_64.dmg",
  "url_specs": {},
  "appcast": null,
  "version": "2023-05-14.e7dc30c.master",
  "installed": null,
  "outdated": false,
  "sha256": "0d211c72ddd9a007b1473272ee3d63142b6f31c13a97fa58b37a7bbbd7ed9583",
  "artifacts": [
    {
      "app": [
        "Emacs.app"
      ]
    },
    {
      "binary": [
        "/Applications/Emacs.app/Contents/MacOS/bin/ebrowse"
      ]
    },
    {
      "binary": [
        "/Applications/Emacs.app/Contents/MacOS/bin/emacs"
      ]
    },
    {
      "binary": [
        "/Applications/Emacs.app/Contents/MacOS/bin/emacsclient"
      ]
    },
    {
      "binary": [
        "/Applications/Emacs.app/Contents/MacOS/bin/etags"
      ]
    },
    {
      "binary": [
        "/Applications/Emacs.app/Contents/Resources/include/emacs-module.h",
        {
          "target": "/usr/local/include/emacs-module.h"
        }
      ]
    },
    {
      "binary": [
        "/Applications/Emacs.app/Contents/Resources/site-lisp/subdirs.el",
        {
          "target": "/usr/local/share/emacs/site-lisp/subdirs.el"
        }
      ]
    },
    {
      "manpage": [
        "/Applications/Emacs.app/Contents/Resources/man/man1/ebrowse.1.gz"
      ]
    },
    {
      "manpage": [
        "/Applications/Emacs.app/Contents/Resources/man/man1/emacs.1.gz"
      ]
    },
    {
      "manpage": [
        "/Applications/Emacs.app/Contents/Resources/man/man1/emacsclient.1.gz"
      ]
    },
    {
      "manpage": [
        "/Applications/Emacs.app/Contents/Resources/man/man1/etags.1.gz"
      ]
    },
    {
      "zap": [
        {
          "trash": [
            "~/Library/Caches/org.gnu.Emacs",
            "~/Library/Preferences/org.gnu.Emacs.plist",
            "~/Library/Saved Application State/org.gnu.Emacs.savedState"
          ]
        }
      ]
    }
  ],
  "caveats": null,
  "depends_on": {
    "macos": {
      ">=": [
        "11"
      ]
    }
  },
  "conflicts_with": {
    "cask": [
      "emacs-app",
      "emacs-app-good",
      "emacs-app-nightly-28",
      "emacs-app-nightly-29",
      "emacs-app-pretest",
      "emacs",
      "emacs-nightly",
      "emacs-pretest",
      "emacs-mac",
      "emacs-mac-spacemacs-icon"
    ],
    "formula": [
      "emacs",
      "emacs-mac"
    ]
  },
  "container": null,
  "auto_updates": null,
  "tap_git_head": "0b0c8d1dd10320db3cd2187c43944cc586103ed7",
  "languages": [],
  "ruby_source_path": "Casks/emacs-app-nightly.rb",
  "ruby_source_checksum": {
    "sha256": "bae21cd1515680424cf057e05793b09b5fc9c29e41c93a667f356009ee8eff8c"
  }
}
